Workbook

Sheet COVER
A1: BUDGET VS ACTUAL VARIANCE TRACKER
A2: Nova Tech Soutions Pvt.Ltd.|FY 2024-25|IT Services|Bengaluru,India
A4: Project Details
A5: Prepared by | B5: Muhammed Ramees A
A6: Qualification | B6: CMA (USA) | BCOM Graduate
A7: Financial Year | B7: April 2024-March 2025
A8: Currency | B8: Indian Rupees(INR)-all amounts in full ₹
A9: Company | B9: NovaTech Soulutions Pvt.Ltd.IT Services,Bengaluru
A10: Departments Tracked | B10: 6 Departments |12 Months|72 Data points
A11: Data type | B11: Fictional -Created for Portfolio Demonstration Purposes
A12: Tool used | B12: Microsoft Excel-Advanced Excel techniques
A14: How to use this file
A15: Step 1 --Go to the Assumptions sheet and review department budgets
A16: Step 2-- Go to the Data entry sheet to view or enter monthly actual spend
A17: Step 3-- The Calculations sheet updates automatically — do not type here
A18: Step 4-- Go to the Dashboard sheet for charts, KPIs and variance summary
A19: Note — Never type in green or yellow cells anywhere in this workbook
A21: DISCLAIMER: All financial data in this workbook is entirely fictional and created solely for portfolio and skill demonstration purposes. NovaTech Solutions Pvt. Ltd. is a fictional company. This workbook does not represent any real company, organisation, or financial event.

Sheet ASSUMPTIONS
A1: Budget Assumptions--FY 2024-25
A3: Department | B3: Annual Budget (₹) | C3: 45383 | D3: 45413 | E3: 45444 | F3: 45474 | G3: 45505 | H3: 45536 | I3: 45566 | J3: 45597 | K3: 45627 | L3: 45658 | M3: 45689 | N3: 45717 | O3: Total Check
A4: Sales & Marketing | B4: 4800000 | C4: =B4/12 -> 400000 | D4: 400000 | E4: 400000 | F4: 400000 | G4: 400000 | H4: 400000 | I4: 400000 | J4: 400000 | K4: 400000 | L4: 400000 | M4: 400000 | N4: 400000 | O4: =SUM(C4:N4) -> 4800000
A5: Technology & IT | B5: 3600000 | C5: =B5/12 -> 300000 | D5: 300000 | E5: 300000 | F5: 300000 | G5: 300000 | H5: 300000 | I5: 300000 | J5: 300000 | K5: 300000 | L5: 300000 | M5: 300000 | N5: 300000 | O5: =SUM(C5:N5) -> 3600000
A6: Human Resources | B6: 1800000 | C6: =B6/12 -> 150000 | D6: 150000 | E6: 150000 | F6: 150000 | G6: 150000 | H6: 150000 | I6: 150000 | J6: 150000 | K6: 150000 | L6: 150000 | M6: 150000 | N6: 150000 | O6: =SUM(C6:N6) -> 1800000
A7: Operations | B7: 3000000 | C7: =B7/12 -> 250000 | D7: 250000 | E7: 250000 | F7: 250000 | G7: 250000 | H7: 250000 | I7: 250000 | J7: 250000 | K7: 250000 | L7: 250000 | M7: 250000 | N7: 250000 | O7: =SUM(C7:N7) -> 3000000
A8: Finance & Admin | B8: 1200000 | C8: =B8/12 -> 100000 | D8: 100000 | E8: 100000 | F8: 100000 | G8: 100000 | H8: 100000 | I8: 100000 | J8: 100000 | K8: 100000 | L8: 100000 | M8: 100000 | N8: 100000 | O8: =SUM(C8:N8) -> 1200000
A9: Research & Development | B9: 2400000 | C9: =B9/12 -> 200000 | D9: 200000 | E9: 200000 | F9: 200000 | G9: 200000 | H9: 200000 | I9: 200000 | J9: 200000 | K9: 200000 | L9: 200000 | M9: 200000 | N9: 200000 | O9: =SUM(C9:N9) -> 2400000
A11: TOTAL | B11: =SUM(B4:B9) -> 16800000 | C11: =SUM(C4:C9) -> 1400000 | D11: =SUM(D4:D9) -> 1400000 | E11: =SUM(E4:E9) -> 1400000 | F11: =SUM(F4:F9) -> 1400000 | G11: =SUM(G4:G9) -> 1400000 | H11: =SUM(H4:H9) -> 1400000 | I11: =SUM(I4:I9) -> 1400000 | ... O11: =SUM(O4:O9) -> 16800000
A13: Note: Monthly budgets are calculated as Annual Budget ÷ 12 (equal monthly split). To use seasonal weightings, replace the ÷12 formula with department-specific monthly percentages.

Sheet DATA ENTRY
A1: Monthly Actual Spend --Data Entry | Nova Tech Solutions Pvt .Ltd| FY 2024-25
A2: Use the dropdowns in column B and C .Only type in the blue cells .Do not edit yellow or grey cells
A3: No. | B3: Month | C3: Department | D3: Actual Spend (₹) | E3: Notes / Remarks
A4: 1 | B4: 45383 | C4: Sales & Marketing | D4: 438000 | E4: UAE client pitch-- increased campaign and travel spend
A5: 2 | B5: 45383 | C5: Technology & IT | D5: 291000 | E5: Sever upgrade delayed to May --under budget this month
A6: 3 | B6: 45383 | C6: Human Resources | D6: 152000 | E6: Minor payroll adjustment for new joiner
A7: 4 | B7: 45383 | C7: Operations | D7: 263000 | E7: March vendor invoice processed late — included this month
A8: 5 | B8: 45383 | C8: Finance & Admin | D8: 97000 | E8: Renegotiated office supply contract — cost savings achieved
A9: 6 | B9: 45383 | C9: Research & Development | D9: 205000 | E9: New prototype tool subscription commenced
A10: 7 | B10: 45413 | C10: Sales & Marketing | D10: 471000 | E10: New prototype tool subscription commenced
A11: 8 | B11: 45413 | C11: Technology & IT | D11: 318000 | E11: New prototype tool subscription commenced
A12: 9 | B12: 45413 | C12: Human Resources | D12: 147000 | E12: Below budget — one vacancy unfilled, recruitment on hold
A13: 10 | B13: 45413 | C13: Operations | D13: 244000 | E13: Utility bills lower due to mild weather — under budget
A14: 11 | B14: 45413 | C14: Finance & Admin | D14: 104000 | E14: Annual software licence renewal — minor overspend
A15: 12 | B15: 45413 | C15: Research & Development | D15: 196000 | E15: Prototype phase paused pending design review
... A75: 72 | B75: 45717 | C75: Research & Development | D75: 221000 | E75: Prototype delivered — final developer sign-off and documentation

Sheet CALCULATIONS
A1: Variance Analysis- FY 2024-25| Nova Tech Solutions Pvt.Ltd.
A3: Department | B3: Metric | C3: 45383 | D3: 45413 | E3: 45444 | F3: 45474 | G3: 45505 | H3: 45536 | I3: 45566 | J3: 45597 | K3: 45627 | L3: 45658 | M3: 45689 | N3: 45717 | O3: Full Year | P3: Var % | Q3: Status
A4: Sales & Marketing | B4: Budget (₹) | C4: =ASSUMPTIONS!C4 -> 400000 | D4: =ASSUMPTIONS!D4 -> 400000 | E4: =ASSUMPTIONS!E4 -> 400000 | F4: =ASSUMPTIONS!F4 -> 400000 | G4: =ASSUMPTIONS!G4 -> 400000 | H4: =ASSUMPTIONS!H4 -> 400000 | I4: =ASSUMPTIONS!I4 -> 400000 | J4: =ASSUMPTIONS!J4 -> 400000 | ... N4: =ASSUMPTIONS!N4 -> 400000 | O4: =SUM(C4:N4) -> 4800000
B5: Actual (₹) | C5: =SUMIFS(ActualData[Actual Spend (₹)],ActualData[Department],$A4,ActualData[Month],C$3) -> 438000 | D5: =SUMIFS(ActualData[Actual Spend (₹)],ActualData[Department],$A4,ActualData[Month],D$3) -> 471000 | E5: =SUMIFS(ActualData[Actual Spend (₹)],ActualData[Department],$A4,ActualData[Month],E$3) -> 485000 | F5: =SUMIFS(ActualData[Actual Spend (₹)],ActualData[Department],$A4,ActualData[Month],F$3) -> 392000 | G5: =SUMIFS(ActualData[Actual Spend (₹)],ActualData[Department],$A4,ActualData[Month],G$3) -> 388000 | H5: =SUMIFS(ActualData[Actual Spend (₹)],ActualData[Department],$A4,ActualData[Month],H$3) -> 412000 | I5: =SUMIFS(ActualData[Actual Spend (₹)],ActualData[Department],$A4,ActualData[Month],I$3) -> 428000 | J5: =SUMIFS(ActualData[Actual Spend (₹)],ActualData[Department],$A4,ActualData[Month],J$3) -> 376000 | ... N5: =SUMIFS(ActualData[Actual Spend (₹)],ActualData[Department],$A4,ActualData[Month],N$3) -> 451000 | O5: =SUM(C5:N5) -> 5047000
B6: Variance (₹) | C6: =C5-C4 -> 38000 | D6: =D5-D4 -> 71000 | E6: =E5-E4 -> 85000 | F6: =F5-F4 -> -8000 | G6: =G5-G4 -> -12000 | H6: =H5-H4 -> 12000 | I6: =I5-I4 -> 28000 | J6: =J5-J4 -> -24000 | ... O6: =O5-O4 -> 247000 | P6: =IF(O4=0,0,O6/O4) -> 0.051458333 | Q6: =IF(P6>0.1,"OVER BUDGET",IF(P6>0.05,"WATCH",IF(P6>=-0.05,"ON TRACK","UNDER BUDGET"))) -> WATCH
A7: Technology & IT | B7: Budget (₹) | C7: =ASSUMPTIONS!C5 -> 300000 | D7: =ASSUMPTIONS!D5 -> 300000 | E7: =ASSUMPTIONS!E5 -> 300000 | F7: =ASSUMPTIONS!F5 -> 300000 | G7: =ASSUMPTIONS!G5 -> 300000 | H7: =ASSUMPTIONS!H5 -> 300000 | I7: =ASSUMPTIONS!I5 -> 300000 | J7: =ASSUMPTIONS!J5 -> 300000 | ... N7: =ASSUMPTIONS!N5 -> 300000 | O7: =SUM(C7:N7) -> 3600000
B8: Actual (₹) | C8: =SUMIFS(ActualData[Actual Spend (₹)],ActualData[Department],$A4,ActualData[Month],C$3) -> 438000 | D8: =SUMIFS(ActualData[Actual Spend (₹)],ActualData[Department],$A7,ActualData[Month],D$3) -> 318000 | E8: =SUMIFS(ActualData[Actual Spend (₹)],ActualData[Department],$A7,ActualData[Month],E$3) -> 288000 | F8: =SUMIFS(ActualData[Actual Spend (₹)],ActualData[Department],$A7,ActualData[Month],F$3) -> 342000 | G8: =SUMIFS(ActualData[Actual Spend (₹)],ActualData[Department],$A7,ActualData[Month],G$3) -> 356000 | H8: =SUMIFS(ActualData[Actual Spend (₹)],ActualData[Department],$A7,ActualData[Month],H$3) -> 361000 | I8: =SUMIFS(ActualData[Actual Spend (₹)],ActualData[Department],$A7,ActualData[Month],I$3) -> 279000 | J8: =SUMIFS(ActualData[Actual Spend (₹)],ActualData[Department],$A7,ActualData[Month],J$3) -> 283000 | K8: =SUMIFS(ActualData[Actual Spend (₹)],ActualData[Department],$A7,ActualData[Month],K$3) -> 272000 | ... N8: =SUMIFS(ActualData[Actual Spend (₹)],ActualData[Department],$A7,ActualData[Month],N$3) -> 309000 | O8: =SUM(C8:N8) -> 3847000
B9: Variance (₹) | C9: =C8-C7 -> 138000 | D9: =D8-D7 -> 18000 | E9: =E8-E7 -> -12000 | F9: =F8-F7 -> 42000 | G9: =G8-G7 -> 56000 | H9: =H8-H7 -> 61000 | I9: =I8-I7 -> -21000 | J9: =J8-J7 -> -17000 | ... O9: =O8-O7 -> 247000 | P9: =IF(O7=0,0,O9/O7) -> 0.068611111 | Q9: =IF(P9>0.1,"OVER BUDGET",IF(P9>0.05,"WATCH",IF(P9>=-0.05,"ON TRACK","UNDER BUDGET"))) -> WATCH
A10: Human Resources | B10: Budget (₹) | C10: =ASSUMPTIONS!C6 -> 150000 | D10: =ASSUMPTIONS!D6 -> 150000 | E10: =ASSUMPTIONS!E6 -> 150000 | F10: =ASSUMPTIONS!F6 -> 150000 | G10: =ASSUMPTIONS!G6 -> 150000 | H10: =ASSUMPTIONS!H6 -> 150000 | I10: =ASSUMPTIONS!I6 -> 150000 | J10: =ASSUMPTIONS!J6 -> 150000 | ... N10: =ASSUMPTIONS!N6 -> 150000 | O10: =SUM(C10:N10) -> 1800000
B11: Actual (₹) | C11: =SUMIFS(ActualData[Actual Spend (₹)],ActualData[Department],$A10,ActualData[Month],C$3) -> 152000 | D11: =SUMIFS(ActualData[Actual Spend (₹)],ActualData[Department],$A10,ActualData[Month],D$3) -> 147000 | E11: =SUMIFS(ActualData[Actual Spend (₹)],ActualData[Department],$A10,ActualData[Month],E$3) -> 153000 | F11: =SUMIFS(ActualData[Actual Spend (₹)],ActualData[Department],$A10,ActualData[Month],F$3) -> 149000 | G11: =SUMIFS(ActualData[Actual Spend (₹)],ActualData[Department],$A10,ActualData[Month],G$3) -> 174000 | H11: =SUMIFS(ActualData[Actual Spend (₹)],ActualData[Department],$A10,ActualData[Month],H$3) -> 189000 | I11: =SUMIFS(ActualData[Actual Spend (₹)],ActualData[Department],$A10,ActualData[Month],I$3) -> 193000 | J11: =SUMIFS(ActualData[Actual Spend (₹)],ActualData[Department],$A10,ActualData[Month],J$3) -> 191000 | ... N11: =SUMIFS(ActualData[Actual Spend (₹)],ActualData[Department],$A10,ActualData[Month],N$3) -> 164000 | O11: =SUM(C11:N11) -> 1987000
B12: Variance (₹) | C12: =C11-C10 -> 2000 | D12: =D11-D10 -> -3000 | E12: =E11-E10 -> 3000 | F12: =F11-F10 -> -1000 | G12: =G11-G10 -> 24000 | H12: =H11-H10 -> 39000 | I12: =I11-I10 -> 43000 | J12: =J11-J10 -> 41000 | ... O12: =O11-O10 -> 187000 | P12: =IF(O10=0,0,O12/O10) -> 0.10388889 | Q12: =IF(P12>0.1,"OVER BUDGET",IF(P12>0.05,"WATCH",IF(P12>=-0.05,"ON TRACK","UNDER BUDGET"))) -> OVER BUDGET
A13: Operations | B13: Budget (₹) | C13: =ASSUMPTIONS!C7 -> 250000 | D13: =ASSUMPTIONS!D7 -> 250000 | E13: =ASSUMPTIONS!E7 -> 250000 | F13: =ASSUMPTIONS!F7 -> 250000 | G13: =ASSUMPTIONS!G7 -> 250000 | H13: =ASSUMPTIONS!H7 -> 250000 | I13: =ASSUMPTIONS!I7 -> 250000 | J13: =ASSUMPTIONS!J7 -> 250000 | ... N13: =ASSUMPTIONS!N7 -> 250000 | O13: =SUM(C13:N13) -> 3000000
B14: Actual (₹) | C14: =SUMIFS(ActualData[Actual Spend (₹)],ActualData[Department],$A13,ActualData[Month],C$3) -> 263000 | D14: =SUMIFS(ActualData[Actual Spend (₹)],ActualData[Department],$A13,ActualData[Month],D$3) -> 244000 | E14: =SUMIFS(ActualData[Actual Spend (₹)],ActualData[Department],$A13,ActualData[Month],E$3) -> 258000 | F14: =SUMIFS(ActualData[Actual Spend (₹)],ActualData[Department],$A13,ActualData[Month],F$3) -> 247000 | G14: =SUMIFS(ActualData[Actual Spend (₹)],ActualData[Department],$A13,ActualData[Month],G$3) -> 252000 | H14: =SUMIFS(ActualData[Actual Spend (₹)],ActualData[Department],$A13,ActualData[Month],H$3) -> 261000 | I14: =SUMIFS(ActualData[Actual Spend (₹)],ActualData[Department],$A13,ActualData[Month],I$3) -> 255000 | J14: =SUMIFS(ActualData[Actual Spend (₹)],ActualData[Department],$A13,ActualData[Month],J$3) -> 248000 | ... N14: =SUMIFS(ActualData[Actual Spend (₹)],ActualData[Department],$A13,ActualData[Month],N$3) -> 272000 | O14: =SUM(C14:N14) -> 3061000
B15: Variance (₹) | C15: =C14-C13 -> 13000 | D15: =D14-D13 -> -6000 | E15: =E14-E13 -> 8000 | F15: =F14-F13 -> -3000 | G15: =G14-G13 -> 2000 | H15: =H14-H13 -> 11000 | I15: =I14-I13 -> 5000 | J15: =J14-J13 -> -2000 | ... O15: =O14-O13 -> 61000 | P15: =IF(O13=0,0,O15/O13) -> 0.020333333 | Q15: =IF(P15>0.1,"OVER BUDGET",IF(P15>0.05,"WATCH",IF(P15>=-0.05,"ON TRACK","UNDER BUDGET"))) -> ON TRACK
A16: Finance & Admin | B16: Budget (₹) | C16: =ASSUMPTIONS!C8 -> 100000 | D16: =ASSUMPTIONS!D8 -> 100000 | E16: =ASSUMPTIONS!E8 -> 100000 | F16: =ASSUMPTIONS!F8 -> 100000 | G16: =ASSUMPTIONS!G8 -> 100000 | H16: =ASSUMPTIONS!H8 -> 100000 | I16: =ASSUMPTIONS!I8 -> 100000 | J16: =ASSUMPTIONS!J8 -> 100000 | ... N16: =ASSUMPTIONS!N8 -> 100000 | O16: =SUM(C16:N16) -> 1200000
B17: Actual (₹) | C17: =SUMIFS(ActualData[Actual Spend (₹)],ActualData[Department],$A16,ActualData[Month],C$3) -> 97000 | D17: =SUMIFS(ActualData[Actual Spend (₹)],ActualData[Department],$A16,ActualData[Month],D$3) -> 104000 | E17: =SUMIFS(ActualData[Actual Spend (₹)],ActualData[Department],$A16,ActualData[Month],E$3) -> 98000 | F17: =SUMIFS(ActualData[Actual Spend (₹)],ActualData[Department],$A16,ActualData[Month],F$3) -> 101000 | G17: =SUMIFS(ActualData[Actual Spend (₹)],ActualData[Department],$A16,ActualData[Month],G$3) -> 96000 | H17: =SUMIFS(ActualData[Actual Spend (₹)],ActualData[Department],$A16,ActualData[Month],H$3) -> 99000 | I17: =SUMIFS(ActualData[Actual Spend (₹)],ActualData[Department],$A16,ActualData[Month],I$3) -> 107000 | J17: =SUMIFS(ActualData[Actual Spend (₹)],ActualData[Department],$A16,ActualData[Month],J$3) -> 103000 | ... N17: =SUMIFS(ActualData[Actual Spend (₹)],ActualData[Department],$A16,ActualData[Month],N$3) -> 109000 | O17: =SUM(C17:N17) -> 1222000
B18: Variance (₹) | C18: =C17-C16 -> -3000 | D18: =D17-D16 -> 4000 | E18: =E17-E16 -> -2000 | F18: =F17-F16 -> 1000 | G18: =G17-G16 -> -4000 | H18: =H17-H16 -> -1000 | I18: =I17-I16 -> 7000 | J18: =J17-J16 -> 3000 | ... O18: =O17-O16 -> 22000 | P18: =IF(O16=0,0,O18/O16) -> 0.018333333 | Q18: =IF(P18>0.1,"OVER BUDGET",IF(P18>0.05,"WATCH",IF(P18>=-0.05,"ON TRACK","UNDER BUDGET"))) -> ON TRACK
A19: Research & Development | B19: Budget (₹) | C19: =ASSUMPTIONS!C9 -> 200000 | D19: =ASSUMPTIONS!D9 -> 200000 | E19: =ASSUMPTIONS!E9 -> 200000 | F19: =ASSUMPTIONS!F9 -> 200000 | G19: =ASSUMPTIONS!G9 -> 200000 | H19: =ASSUMPTIONS!H9 -> 200000 | I19: =ASSUMPTIONS!I9 -> 200000 | J19: =ASSUMPTIONS!J9 -> 200000 | ... N19: =ASSUMPTIONS!N9 -> 200000 | O19: =SUM(C19:N19) -> 2400000
B20: Actual (₹) | C20: =SUMIFS(ActualData[Actual Spend (₹)],ActualData[Department],$A19,ActualData[Month],C$3) -> 205000 | D20: =SUMIFS(ActualData[Actual Spend (₹)],ActualData[Department],$A19,ActualData[Month],D$3) -> 196000 | E20: =SUMIFS(ActualData[Actual Spend (₹)],ActualData[Department],$A19,ActualData[Month],E$3) -> 211000 | F20: =SUMIFS(ActualData[Actual Spend (₹)],ActualData[Department],$A19,ActualData[Month],F$3) -> 223000 | G20: =SUMIFS(ActualData[Actual Spend (₹)],ActualData[Department],$A19,ActualData[Month],G$3) -> 208000 | H20: =SUMIFS(ActualData[Actual Spend (₹)],ActualData[Department],$A19,ActualData[Month],H$3) -> 197000 | I20: =SUMIFS(ActualData[Actual Spend (₹)],ActualData[Department],$A19,ActualData[Month],I$3) -> 214000 | J20: =SUMIFS(ActualData[Actual Spend (₹)],ActualData[Department],$A19,ActualData[Month],J$3) -> 219000 | ... N20: =SUMIFS(ActualData[Actual Spend (₹)],ActualData[Department],$A19,ActualData[Month],N$3) -> 221000 | O20: =SUM(C20:N20) -> 2505000
B21: Variance (₹) | C21: =C20-C19 -> 5000 | D21: =D20-D19 -> -4000 | E21: =E20-E19 -> 11000 | F21: =F20-F19 -> 23000 | G21: =G20-G19 -> 8000 | H21: =H20-H19 -> -3000 | I21: =I20-I19 -> 14000 | J21: =J20-J19 -> 19000 | ... O21: =O20-O19 -> 105000 | P21: =IF(O19=0,0,O21/O19) -> 0.04375 | Q21: =IF(P21>0.1,"OVER BUDGET",IF(P21>0.05,"WATCH",IF(P21>=-0.05,"ON TRACK","UNDER BUDGET"))) -> ON TRACK
A23: GRAND TOTAL | C23: =SUM(C4,C7,C10,C13,C16,C19) -> 1400000 | D23: =SUM(D4,D7,D10,D13,D16,D19) -> 1400000 | E23: =SUM(E4,E7,E10,E13,E16,E19) -> 1400000 | F23: =SUM(F4,F7,F10,F13,F16,F19) -> 1400000 | G23: =SUM(G4,G7,G10,G13,G16,G19) -> 1400000 | H23: =SUM(H4,H7,H10,H13,H16,H19) -> 1400000 | I23: =SUM(I4,I7,I10,I13,I16,I19) -> 1400000 | J23: =SUM(J4,J7,J10,J13,J16,J19) -> 1400000 | ... O23: =SUM(O4,O7,O10,O13,O16,O19) -> 16800000
C24: =SUM(C5,C8,C11,C14,C17,C20) -> 1593000 | D24: =SUM(D5,D8,D11,D14,D17,D20) -> 1480000 | E24: =SUM(E5,E8,E11,E14,E17,E20) -> 1493000 | F24: =SUM(F5,F8,F11,F14,F17,F20) -> 1454000 | G24: =SUM(G5,G8,G11,G14,G17,G20) -> 1474000 | H24: =SUM(H5,H8,H11,H14,H17,H20) -> 1519000 | I24: =SUM(I5,I8,I11,I14,I17,I20) -> 1476000 | J24: =SUM(J5,J8,J11,J14,J17,J20) -> 1420000 | ... O24: =SUM(O5,O8,O11,O14,O17,O20) -> 17669000
C25: =C24-C23 -> 193000 | D25: =D24-D23 -> 80000 | E25: =E24-E23 -> 93000 | F25: =F24-F23 -> 54000 | G25: =G24-G23 -> 74000 | H25: =H24-H23 -> 119000 | I25: =I24-I23 -> 76000 | J25: =J24-J23 -> 20000 | ... O25: =O24-O23 -> 869000

Sheet DASHBOARD
B1: Nova Tech Solutions Pvt. Ltd.- Budget vs Actual Dashboard
B3: FY 2024-25 | IT Services | Bengaluru,India | All amounts in Indian Rupees (₹) | P3: Department | Q3: Variance %
P4: Sales & Marketing | Q4: =CALCULATIONS!P6 -> 0.051458333
B5: TOTAL ANNUAL BUDGET | E5: TOTAL ACTUAL SPEND | H5: FULL YEAR VARIANCE | K5: VARIANCE % | P5: Technology & IT | Q5: =CALCULATIONS!P9 -> 0.068611111
P6: Human Resources | Q6: =CALCULATIONS!P12 -> 0.10388889
P7: Operations | Q7: =CALCULATIONS!P15 -> 0.020333333
B8: =CALCULATIONS!O23 -> 16800000 | E8: =CALCULATIONS!O24 -> 17669000 | H8: =CALCULATIONS!O25 -> 869000 | K8: =CALCULATIONS!O25/CALCULATIONS!O23 -> 0.05172619 | P8: Finance & Admin | Q8: =CALCULATIONS!P18 -> 0.018333333
P9: Research & development | Q9: =CALCULATIONS!P21 -> 0.04375
B11: FY 2024-25 Plan | E11: Full Year Actuals | H11: Over Budget | K11: Above Plan
P12: Month | Q12: Budget | R12: Actual
P13: 45383 | Q13: =CALCULATIONS!C23 -> 1400000 | R13: =CALCULATIONS!C24 -> 1593000
P14: 45413 | Q14: =CALCULATIONS!D23 -> 1400000 | R14: =CALCULATIONS!D24 -> 1480000
P15: 45444 | Q15: =CALCULATIONS!E23 -> 1400000 | R15: =CALCULATIONS!E24 -> 1493000
P16: 45474 | Q16: =CALCULATIONS!F23 -> 1400000 | R16: =CALCULATIONS!F24 -> 1454000
P17: 45505 | Q17: =CALCULATIONS!G23 -> 1400000 | R17: =CALCULATIONS!G24 -> 1474000
P18: 45536 | Q18: =CALCULATIONS!H23 -> 1400000 | R18: =CALCULATIONS!H24 -> 1519000
P19: 45566 | Q19: =CALCULATIONS!I23 -> 1400000 | R19: =CALCULATIONS!I24 -> 1476000
P20: 45597 | Q20: =CALCULATIONS!J23 -> 1400000 | R20: =CALCULATIONS!J24 -> 1420000
P21: 45627 | Q21: =CALCULATIONS!K23 -> 1400000 | R21: =CALCULATIONS!K24 -> 1312000
P22: 45658 | Q22: =CALCULATIONS!L23 -> 1400000 | R22: =CALCULATIONS!L24 -> 1439000
P23: 45689 | Q23: =CALCULATIONS!M23 -> 1400000 | R23: =CALCULATIONS!M24 -> 1483000
P24: 45717 | Q24: =CALCULATIONS!N23 -> 1400000 | R24: =CALCULATIONS!N24 -> 1526000
B30: Department | C30: Annual Budget(₹) | D30: Full Year Actual (₹) | E30: Variance (₹) | F30: Variance (%) | G30: Status
B31: Sales & Marketing | C31: =CALCULATIONS!O4 -> 4800000 | D31: =CALCULATIONS!O5 -> 5047000 | E31: =CALCULATIONS!O6 -> 247000 | F31: =CALCULATIONS!P6 -> 0.051458333 | G31: =CALCULATIONS!Q6 -> WATCH
B32: Technology & IT | C32: =CALCULATIONS!O7 -> 3600000 | D32: =CALCULATIONS!O8 -> 3847000 | E32: =CALCULATIONS!O9 -> 247000 | F32: =CALCULATIONS!P9 -> 0.068611111 | G32: =CALCULATIONS!Q9 -> WATCH
B33: Human Resources | C33: =CALCULATIONS!O10 -> 1800000 | D33: =CALCULATIONS!O11 -> 1987000 | E33: =CALCULATIONS!O12 -> 187000 | F33: =CALCULATIONS!P12 -> 0.10388889 | G33: =CALCULATIONS!Q12 -> OVER BUDGET
B34: Operations | C34: =CALCULATIONS!O13 -> 3000000 | D34: =CALCULATIONS!O14 -> 3061000 | E34: =CALCULATIONS!O15 -> 61000 | F34: =CALCULATIONS!P15 -> 0.020333333 | G34: =CALCULATIONS!Q15 -> ON TRACK
B35: Finance & Admin | C35: =CALCULATIONS!O16 -> 1200000 | D35: =CALCULATIONS!O17 -> 1222000 | E35: =CALCULATIONS!O18 -> 22000 | F35: =CALCULATIONS!P18 -> 0.018333333 | G35: =CALCULATIONS!Q18 -> ON TRACK
B36: Research & Development | C36: =CALCULATIONS!O19 -> 2400000 | D36: =CALCULATIONS!O20 -> 2505000 | E36: =CALCULATIONS!O21 -> 105000 | F36: =CALCULATIONS!P21 -> 0.04375 | G36: =CALCULATIONS!Q21 -> ON TRACK
B62: NovaTech Solutions Pvt. Ltd. | Fictional data — for portfolio demonstration only | Prepared by Muhammed Ramees A | CMA (USA)

Sheet RAW DATA
A1: RAW DATA --Source Reference
A3: All actual spend data is entered in the Data Entry sheet and referenced here. The ActualData table in Data Entry sheet contains all 72 transaction records for FY 2024-25. This sheet serves as a data source reference tab.
A5: To view all 72 rows of actual data — go to the Data Entry sheet.
